sonos_extras/__init__.py
sonos_extras/module.py
sonos_extras/bin/SonosExtrasCLI.py
sonos_extras/bin/__init__.py
sonos_extras/tests/__init__.py
sonos_extras/tests/test_cli.py
sonos_extras/tests/test_module.py
sonos_extras-0.1.20.dist-info/METADATA
sonos_extras-0.1.20.dist-info/WHEEL
sonos_extras-0.1.20.dist-info/entry_points.txt
sonos_extras-0.1.20.dist-info/top_level.txt
sonos_extras-0.1.20.dist-info/RECORD
