Metadata-Version: 2.1
Name: sonos-extras
Version: 0.1.20
Summary: Some extra useful commands for Sonos systems, based on SoCo.
Home-page: https://pypi.org/project/sonos-extras/
Author: MaziarA
Author-email: maziara2@gmail.com
License: MIT
Platform: UNKNOWN
Classifier: Development Status :: 4 - Beta
Classifier: License :: OSI Approved :: MIT License
Classifier: Programming Language :: Python
Classifier: Programming Language :: Python :: 3.8
Requires-Dist: python-dateutil
Requires-Dist: soco (==0.19)
